{
    "recipesEndpoint": "",
    "packages": [
        {
            "requirement": "dev-split-scenarios as 2.3.x-dev",
            "repositoryUrl": "https://github.com/ezsystems/ezplatform-form-builder",
            "package": "ezsystems/ezplatform-form-builder",
            "shouldBeAddedAsVCS": true
        },
        {
            "requirement": "dev-split-scenarios as 2.3.x-dev",
            "repositoryUrl": "https://github.com/ezsystems/ezplatform-page-builder",
            "package": "ezsystems/ezplatform-page-builder",
            "shouldBeAddedAsVCS": true
        },
        {
            "requirement": "dev-split-scenarios as 2.3.x-dev",
            "repositoryUrl": "https://github.com/ezsystems/ezplatform-admin-ui",
            "package": "ezsystems/ezplatform-admin-ui",
            "shouldBeAddedAsVCS": false
        },
        {
            "requirement": "dev-parallel-envs as 8.3.x-dev",
            "repositoryUrl": "https://github.com/ezsystems/BehatBundle",
            "package": "ezsystems/behatbundle",
            "shouldBeAddedAsVCS": false
        }
    ]
}